MANIFEST.in
NEWS.txt
README.rst
setup.py
src/pywhmcs7/__init__.py
src/pywhmcs7/whmcs.py
src/pywhmcs7.egg-info/PKG-INFO
src/pywhmcs7.egg-info/SOURCES.txt
src/pywhmcs7.egg-info/dependency_links.txt
src/pywhmcs7.egg-info/entry_points.txt
src/pywhmcs7.egg-info/not-zip-safe
src/pywhmcs7.egg-info/requires.txt
src/pywhmcs7.egg-info/top_level.txt