Metadata-Version: 1.1
Name: pywhmcs7
Version: 1.0.1
Summary: WHMCS 7.x Client Library
Home-page: https://github.com/riesal/pywhmcs7
Author: Muhammad Fahrizal Rahman
Author-email: riesal@gmail.com
License: Gnu General Public License v3
Keywords: whmcs v.7.x library http api
Platform: UNKNOWN
Classifier: Development Status :: 1 - Planning
Classifier: Development Status :: 2 - Pre-Alpha
Classifier: Environment :: Console
Classifier: Intended Audience :: Developers
Classifier: Intended Audience :: System Administrators
Classifier: License :: OSI Approved :: GNU General Public License v3 (GPLv3)
Classifier: Natural Language :: English
Classifier: Natural Language :: Indonesian
Classifier: Operating System :: Microsoft :: Windows
Classifier: Operating System :: POSIX :: Linux
Classifier: Programming Language :: Python :: 2.7
Classifier: Topic :: Internet :: WWW/HTTP
